.gitignore
MANIFEST.in
README.txt
setup.py
collective/__init__.py
collective.rolereport.egg-info/PKG-INFO
collective.rolereport.egg-info/SOURCES.txt
collective.rolereport.egg-info/dependency_links.txt
collective.rolereport.egg-info/entry_points.txt
collective.rolereport.egg-info/namespace_packages.txt
collective.rolereport.egg-info/not-zip-safe
collective.rolereport.egg-info/requires.txt
collective.rolereport.egg-info/top_level.txt
collective/rolereport/__init__.py
collective/rolereport/configure.zcml
collective/rolereport/rolereport.pt
collective/rolereport/rolereport.py
collective/rolereport/rolereportmessage.pt
docs/HISTORY.txt
docs/LICENSE.txt