Metadata-Version: 1.1
Name: collective.rolereport
Version: 1.1
Summary: Creates a report on what users have which roles
Home-page: http://www.colliberty.com/
Author: Colliberty
Author-email: info@colliberty.com
License: GPL
Keywords: web zope plone
Platform: UNKNOWN
Classifier: Framework :: Plone
Classifier: Programming Language :: Python
Classifier: Programming Language :: Python :: 2.4
